faceapi/add_face.py
faceapi/demo.py
faceapi/detector.py
faceapi/recog.py
faceapi-0.1.2.dist-info/LICENCE.txt
faceapi-0.1.2.dist-info/METADATA
faceapi-0.1.2.dist-info/WHEEL
faceapi-0.1.2.dist-info/top_level.txt
faceapi-0.1.2.dist-info/RECORD
