Metadata-Version: 1.0
Name: faceapi
Version: 0.1.2
Summary: Face detector and recognition
Home-page: UNKNOWN
Author: Ellery Wang
Author-email: elleryq92@gmail.com
License: UNKNOWN
Platform: UNKNOWN
